ots_eval/__init__.py
ots_eval/clustering/__init__.py
ots_eval/clustering/cots.py
ots_eval/clustering/example.py
ots_eval/outlier_detection/__init__.py
ots_eval/outlier_detection/dact.py
ots_eval/outlier_detection/doots.py
ots_eval/outlier_detection/example.py
ots_eval/outlier_detection/reference_histogram_outlier.py
ots_eval/stability_evaluation/__init__.py
ots_eval/stability_evaluation/close.py
ots_eval/stability_evaluation/example.py
ots_eval/stability_evaluation/fcsets.py
ots_eval-0.0.4.dist-info/LICENSE
ots_eval-0.0.4.dist-info/METADATA
ots_eval-0.0.4.dist-info/WHEEL
ots_eval-0.0.4.dist-info/top_level.txt
ots_eval-0.0.4.dist-info/RECORD
