Metadata-Version: 2.1
Name: ots-eval
Version: 0.0.4
Summary: Over-Time Stability Evaluation
Home-page: https://github.com/tatusch/ots-eval
Author: Martha Krakowski, Gerhard Klassen
Author-email: martha.krakowski@hhu.de, gerhard.klassen@hhu.de
License: UNKNOWN
Project-URL: Source Code, https://github.com/tatusch/ots-eval
Platform: UNKNOWN
Classifier: Programming Language :: Python :: 3
Classifier: License :: OSI Approved :: BSD License
Classifier: Operating System :: OS Independent
Requires-Python: >=3.7
Requires-Dist: pandas (>=1.0.0)
Requires-Dist: numpy (>=1.19.2)
Requires-Dist: scipy (>=1.3.0)
